pyscada/__init__.py
pyscada/smbus/__init__.py
pyscada/smbus/admin.py
pyscada/smbus/apps.py
pyscada/smbus/device.py
pyscada/smbus/models.py
pyscada/smbus/signals.py
pyscada/smbus/worker.py
pyscada/smbus/devices/__init__.py
pyscada/smbus/devices/gim_tracker.py
pyscada/smbus/devices/ups_pico.py
pyscada/smbus/migrations/0001_initial.py
pyscada/smbus/migrations/0002_auto_20170225_0908.py
pyscada/smbus/migrations/0003_extendedsmbusdevice_extendedsmbusvariable.py
pyscada/smbus/migrations/0004_auto_20191004_0912.py
pyscada/smbus/migrations/0005_auto_20201104_1447.py
pyscada/smbus/migrations/0006_smbusdevice_instrument_handler.py
pyscada/smbus/migrations/0007_devicehandler_migration.py
pyscada/smbus/migrations/0008_remove_smbusdevice_instrument.py
pyscada/smbus/migrations/0009_delete_smbusdevicehandler.py
pyscada/smbus/migrations/0010_auto_20210601_1444.py
pyscada/smbus/migrations/0011_auto_20220105_1013.py
pyscada/smbus/migrations/0012_devicehandler_migration.py
pyscada/smbus/migrations/0013_remove_smbusdevice_instrument_handler.py
pyscada/smbus/migrations/0014_add_device_protocol.py
pyscada/smbus/migrations/__init__.py
pyscada_smbus-0.8.0.dist-info/AUTHORS
pyscada_smbus-0.8.0.dist-info/LICENSE
pyscada_smbus-0.8.0.dist-info/METADATA
pyscada_smbus-0.8.0.dist-info/WHEEL
pyscada_smbus-0.8.0.dist-info/top_level.txt
pyscada_smbus-0.8.0.dist-info/RECORD
